polygonscan/__init__.py
polygonscan/polygonscan.py
polygonscan/configs/__init__.py
polygonscan/configs/stable.json
polygonscan/core/__init__.py
polygonscan/core/async_client.py
polygonscan/core/base.py
polygonscan/core/sync_client.py
polygonscan/enums/__init__.py
polygonscan/enums/actions_enum.py
polygonscan/enums/fields_enum.py
polygonscan/enums/modules_enum.py
polygonscan/enums/tags_enum.py
polygonscan/modules/__init__.py
polygonscan/modules/accounts.py
polygonscan/modules/blocks.py
polygonscan/modules/contracts.py
polygonscan/modules/logs.py
polygonscan/modules/proxy.py
polygonscan/modules/stats.py
polygonscan/modules/tokens.py
polygonscan/modules/transactions.py
polygonscan/utils/__init__.py
polygonscan/utils/conversions.py
polygonscan/utils/parsing.py
polygonscan_python-1.0.2.dist-info/LICENSE
polygonscan_python-1.0.2.dist-info/METADATA
polygonscan_python-1.0.2.dist-info/WHEEL
polygonscan_python-1.0.2.dist-info/top_level.txt
polygonscan_python-1.0.2.dist-info/RECORD
